TwitchEventSub/__init__.py
TwitchEventSub/authentication.py
TwitchEventSub/exceptions.py
TwitchEventSub/twitch_event_sub.py
TwitchEventSub/event_types/__init__.py
TwitchEventSub/event_types/event_scopes.py
TwitchEventSub/event_types/event_types.py
TwitchEventSub/event_types/event_versions.py
TwitchEventSub-0.1.4.dist-info/LICENSE
TwitchEventSub-0.1.4.dist-info/METADATA
TwitchEventSub-0.1.4.dist-info/WHEEL
TwitchEventSub-0.1.4.dist-info/top_level.txt
TwitchEventSub-0.1.4.dist-info/RECORD
